{
  "versionCode": 32,
  "versionName": "0.4.28",
  "apkUrl": "https://wardrobe-xuxin.synology.me:8555/android/HomeAI-Android-native-shell-debug-20260621.apk",
  "sha256": "1730f53e2c2ea364bd2e27da2aa8590c8a62ac99502b360d22ccdaa480ca884c",
  "size": 4169794,
  "notes": "Home AI Android native shell v0.4.28: adds an outbound native share bridge for Home AI reply and learning-card PNG images. Web can call HomeAINativeShare.share(request), and the shell writes a bounded verified PNG to cache and opens the Android ACTION_SEND chooser with a FileProvider content URI. Existing inbound system share intake remains unchanged."
}
